Workbook

Sheet 2023
B1: 44927 | C1: 44958 | D1: 44986 | E1: 45017 | F1: 45047 | G1: 45078 | H1: 45108 | I1: 45139 | J1: 45170 | K1: 45200 | L1: 45231 | M1: fechamento 30/11/2023 | N1: Janeiro 2024 (fechamento 31/12/23)
A2: X10 AAI | B2: 21171.84 | C2: 19240.23 | D2: 16771.56 | E2: 41149.59 | F2: 31138.05 | G2: 43495.61 | H2: 55809.27 | I2: 65247.95 | J2: 56333.49 | K2: 50148.56 | L2: 74218.9 | M2: 29106.42 | N2: 39538.79
A3: Banking | B3: 178.43 | C3: 159.68 | D3: 144.9 | E3: 390.23 | F3: 219.2 | G3: 330.51 | H3: 613.88 | I3: 460.99 | J3: 419.72 | K3: 370.72 | L3: 607.79 | M3: 579.38 | N3: 698.21
A4: Previdencia BTG | G4: 172.1 | H4: 173.61 | I4: 192.65 | J4: 247.38 | K4: 278.23 | L4: 330.71 | M4: 350.47 | N4: 387.92
A5: Previdencia ICATU | B5: 62.07 | C5: 123.25 | D5: 105.87 | E5: 173.44 | F5: 152.58 | G5: 17.24 | H5: 13.32 | I5: 12.26 | J5: 12.33 | K5: 10.84 | L5: 11.47 | M5: 11.03 | N5: 11.15
A6: Seguros Omint | H6: 341.44 | I6: 170.72 | J6: 1894.68 | K6: 341.6 | L6: 341.6 | M6: 345.26 | N6: 345.26
A7: Seguros METLIFE | B7: 1247.65 | C7: 249.81 | D7: 1187.22 | E7: 991.27 | F7: 3967.92 | G7: 1118.31 | H7: 1154.75 | I7: 1084.2 | J7: 1198.38 | K7: 1200.15 | L7: 1207.86 | M7: 1453.45 | N7: 1361.95
A8: Seguros MAG
A9: Bonus Incentivo | M9: 149223.52
A10: ITA
A11: TOTAL: | B11: =SUM(B2:B10) -> 22659.99 | C11: =SUM(C2:C10) -> 19772.97 | D11: =SUM(D2:D10) -> 18209.55 | E11: =SUM(E2:E10) -> 42704.53 | F11: =SUM(F2:F10) -> 35477.75 | G11: =SUM(G2:G10) -> 45133.77 | H11: =SUM(H2:H10) -> 58106.27 | I11: =SUM(I2:I10) -> 67168.77 | ... N11: =SUM(N2:N10) -> 42343.28
A12: Incentivos Contrapartida | B12: 10000 | C12: 10000 | D12: 10000 | E12: 10000 | F12: 10000 | G12: 5000 | H12: 0
A13: Incentivos Livres | B13: 0 | C13: 1500 | D13: 1500 | E13: 1500 | F13: 1500 | G13: 1500 | H13: 1500
A14: TOTAL C/ Incentivos | B14: =SUM(B11:B13) -> 32659.99 | C14: =SUM(C11:C13) -> 31272.97 | D14: =SUM(D11:D13) -> 29709.55 | E14: =SUM(E11:E13) -> 54204.53 | F14: =SUM(F11:F13) -> 46977.75 | G14: =SUM(G11:G13) -> 51633.77 | H14: =SUM(H11:H13) -> 59606.27 | I14: =SUM(I11:I13) -> 67168.77 | ... N14: =SUM(N11:N13) -> 42343.28
A15: PL | B15: 23080000 | C15: 26745000 | D15: 29480000 | E15: 33520000 | F15: 37498000 | G15: 38685000 | H15: 40950000 | I15: 44160000 | J15: 48000000 | K15: 51000000 | L15: 55000000 | M15: 59600000 | N15: 59600000
A16: ROA | B16: =B14/B15 -> 0.0014150776 | C16: =C14/C15 -> 0.0011693016 | D16: =D14/D15 -> 0.0010077866 | E16: =E14/E15 -> 0.0016170803 | F16: =F14/F15 -> 0.0012528068 | G16: =G14/G15 -> 0.0013347233 | H16: =H14/H15 -> 0.0014555866 | I16: =I14/I15 -> 0.0015210319 | ... N16: =N14/N15 -> 0.00071045772
A17: ROA Operacional | B17: =B11/B15 -> 0.00098180199 | C17: =C11/C15 -> 0.00073931464 | D17: =D11/D15 -> 0.00061769166 | E17: =E11/E15 -> 0.0012740015 | F17: =F11/F15 -> 0.00094612379 | G17: =G11/G15 -> 0.0011666995 | H17: =H11/H15 -> 0.0014189565 | I17: =I11/I15 -> 0.0015210319 | ... N17: =N11/N15 -> 0.00071045772

Sheet 2024
B1: Mês fechamento
B2: 45292 | C2: 45323 | D2: 45352 | E2: 45383 | F2: 45413 | G2: 45444 | H2: 45474 | I2: 45505 | J2: 45536 | K2: 45566 | L2: 45597 | M2: 45627
A3: X10 AAI | B3: 40775.62 | C3: 44953.78 | D3: 50625.77 | E3: 108764.6 | F3: 91275.57 | G3: 52222 | H3: 87483.09 | I3: 136491.32 | J3: 56611.33 | K3: 92979.398 | L3: 32980.55 | M3: 52553.57
A4: Banking | B4: 132.59 | C4: 1356.67 | D4: 1045.26 | E4: 952.49 | F4: 1165.51 | G4: 758.72 | H4: 760.09 | I4: 1195.86 | J4: 1178.59 | K4: 4065.18 | L4: 896.12 | M4: 3516.39
A5: Previdencia BTG | B5: 503.73 | C5: 449.24 | D5: 1199.42 | E5: 1566.51 | F5: 1558.71 | G5: 1055.27 | H5: 1244.11 | I5: 1262.98 | J5: 1152.51 | K5: 1459.85 | L5: 1322.18 | M5: 1529.8892
A6: Previdencia ICATU | B6: 18.63 | C6: 19.68 | D6: 10.97 | E6: 11.34 | F6: 12.63 | G6: 11.92 | H6: 14.05 | J6: 27.14 | K6: 14.12 | L6: 5.75
A7: Seguros Omint | B7: 345.26 | C7: 517.97 | D7: 517.81 | E7: 517.81 | F7: 219.55 | G7: 219.55
A8: Seguros METLIFE | B8: 1821.02 | C8: 1678.7 | D8: 1814.35 | E8: 2294.36 | F8: 2070.81 | G8: 1740.42 | H8: 3337.47 | J8: 2262.96 | K8: 3390.07 | L8: 2504.3 | M8: 16109.403
A9: Seguros MAG | E9: 200.56 | F9: 29.25 | G9: 29.25 | H9: 29.25
A10: Bonus Incentivo | E10: 166192.71 | M10: 200838.1
A11: CAPTAL | B11: 3377.5 | C11: 11850 | D11: 2700 | E11: 750 | G11: 600 | H11: 675 | I11: 675 | J11: 0
A12: SANTANDER | G12: 7729.24 | H12: 4000 | I12: 9007.15 | J12: 19907.15 | K12: 21030.4 | L12: 30177.91 | M12: 14923.25
A13: ÂNCORA | G13: 720 | H13: 2911.16 | I13: 751.16 | J13: 1502.32 | K13: 751.16 | L13: 751.16 | M13: 751.16
A14: ITA (USD tr) | B14: =4016.26*5 -> 20081.3 | C14: =228.62*5 -> 1143.1 | J14: 1379.09
A15: Frente Corretora | H15: 5070.36 | J15: 0
A16: FRANQ | J16: 375.04
A17: TOTAL: | B17: =SUM(B3:B14) -> 67055.65 | C17: =SUM(C3:C14) -> 61969.14 | D17: =SUM(D3:D14) -> 57913.58 | E17: =SUM(E3:E14) -> 281250.38 | F17: =SUM(F3:F14) -> 96332.03 | G17: =SUM(G3:G14) -> 65086.37 | H17: =SUM(H3:H14) -> 100454.22 | I17: =SUM(I3:I14) -> 149383.47 | ... M17: =SUM(M3:M14) -> 290221.76
A18: Incentivos Contrapartida | B18: 0 | C18: 0
A19: Incentivos Livres | B19: 0 | C19: 0
A20: TOTAL C/ Incentivos | B20: =SUM(B17:B19) -> 67055.65 | C20: =SUM(C17:C19) -> 61969.14 | D20: =SUM(D17:D19) -> 57913.58 | E20: =SUM(E17:E19) -> 281250.38 | F20: =SUM(F17:F19) -> 96332.03 | G20: =SUM(G17:G19) -> 65086.37 | H20: =SUM(H17:H19) -> 100454.22 | I20: =SUM(I17:I19) -> 149383.47 | ... M20: =SUM(M17:M19) -> 290221.76
A21: PL | B21: 58000000 | C21: 62000000 | D21: 66000000 | E21: 69000000 | F21: 78000000 | G21: 81000000 | H21: 84000000 | I21: 99000000 | J21: 87000000 | K21: 99000000 | L21: 104000000 | M21: 125000000
A22: ROA | B22: =B20/B21 -> 0.0011561319 | C22: =C20/C21 -> 0.00099950226 | D22: =D20/D21 -> 0.00087747848 | E22: =E20/E21 -> 0.0040760925 | F22: =F20/F21 -> 0.001235026 | G22: =G20/G21 -> 0.00080353543 | H22: =H20/H21 -> 0.0011958836 | I22: =I20/I21 -> 0.0015089239 | ... M22: =M20/M21 -> 0.0023217741
A27: Amarelo | B27: Faturado
A28: Cinza | B28: Pago
A29: Branco | B29: Pendente

Sheet 2025
A1: Mês fechamento
B2: 45658 | C2: 45689 | D2: 45717 | E2: 45748 | F2: 45778 | G2: 45809 | H2: 45839 | I2: 45870 | J2: 45901 | K2: 45931 | L2: 45962 | M2: 45992
A3: X10 AI | B3: 54627.08
A4: Banking | B4: 3625.8
A5: Previdencia | B5: 1653.0075
A6: Seguros | B6: 39340.615
A7: Seguros MAG
A8: Bonus Incentivo
A9: CAPTAL
A10: SANTANDER | B10: 37588.81
A11: ÂNCORA | B11: 751.16
A12: ITA (USD tr)
A13: Frente Corretora
A14: FRANQ
A15: TOTAL: | B15: =SUM(B3:B12) -> 137586.47 | C15: =SUM(C3:C12) -> 0 | D15: =SUM(D3:D12) -> 0 | E15: =SUM(E3:E12) -> 0 | F15: =SUM(F3:F12) -> 0 | G15: =SUM(G3:G12) -> 0 | H15: =SUM(H3:H12) -> 0 | I15: =SUM(I3:I12) -> 0 | ... M15: =SUM(M3:M12) -> 0
A16: Incentivos Contrapartida | B16: 0 | C16: 0
A17: Incentivos Livres | B17: 0 | C17: 0
A18: TOTAL C/ Incentivos | B18: =SUM(B15:B17) -> 137586.47 | C18: =SUM(C15:C17) -> 0 | D18: =SUM(D15:D17) -> 0 | E18: =SUM(E15:E17) -> 0 | F18: =SUM(F15:F17) -> 0 | G18: =SUM(G15:G17) -> 0 | H18: =SUM(H15:H17) -> 0 | I18: =SUM(I15:I17) -> 0 | ... M18: =SUM(M15:M17) -> 0
A19: PL
A20: ROA | B20: =B18/B19 -> #DIV/0! | C20: =C18/C19 -> #DIV/0! | D20: =D18/D19 -> #DIV/0! | E20: =E18/E19 -> #DIV/0! | F20: =F18/F19 -> #DIV/0! | G20: =G18/G19 -> #DIV/0! | H20: =H18/H19 -> #DIV/0! | I20: =I18/I19 -> #DIV/0! | ... M20: =M18/M19 -> #DIV/0!
A25: Amarelo | B25: Faturado
A26: Cinza | B26: Pago
A27: Branco | B27: Pendente

Sheet Setembro
A1: Centro de custo | B1: Categoria | C1: Nome do cliente ou fornecedor | D1: Valor | E1: Valor baixado (líquido)
A2: Robôs Quantum | B2: Receitas de Serviços | C2: Clientes Quantum | D2: 139680.58 | E2: 139680.58
B3: Materiais de Uso e Consumo | C3: Diversos | D3: -77 | E3: -77
B4: Devoluções por Cancelamento | C4: Clientes Quantum | D4: -2499 | E4: -2499
B5: Comissões de Vendedores | C5: Anderson Cousseau | D5: -185.49 | E5: -185.49
C6: Victor De Lima Pinto | D6: -232.28 | E6: -232.28
C7: Cesar Alberto Guarnieri Junior | D7: -232.28 | E7: -232.28
C8: Lucas Bavaresco | D8: -370.98 | E8: -370.98
C9: Leonardo Berteli Piveta | D9: -603.26 | E9: -603.26
C10: Diego Collaziol | D10: -603.26 | E10: -603.26
C11: Daniel Louis | D11: -1206.52 | E11: -1206.52
C12: Anderson Lopes de Souza | D12: -2646.96 | E12: -2646.96
C13: Danrlei Mallabarba | D13: -2890.59 | E13: -2890.59
C14: Andrei Cousseau | D14: -3553.37 | E14: -3553.37
B15: Software / Licença de Uso | C15: Diversos | D15: -100 | E15: -100
C16: JAX INVESTIMENTOS | D16: -28792.31 | E16: -28792.31
A17: TOTAL | D17: =SUM(D2:D16) -> 95687.28 | E17: =SUM(E2:E16) -> 95687.28
A18: X10 Assessoria de Investimentos | B18: Receitas de Serviços | C18: Banco BTG Pactual | D18: 94001.09 | E18: 94001.08
B19: Rendimentos de Aplicações | C19: X10 Investimentos | D19: 10.4 | E19: 10.4
B20: Impostos retidos em vendas | C20: Banco BTG Pactual | D20: 0 | E20: 0
B21: Tarifas Bancárias | C21: Santander | D21: -9.9 | E21: -9.9
B22: Software / Licença de Uso | C22: Mercado Livre | D22: -41.06 | E22: -41.06
B23: Exames Médicos | C23: MASTERPLAN LTDA | D23: -63.91 | E23: -63.91
B24: Honorários (outros) | C24: APEME | D24: -40 | E24: -40
C25: CIC Garibaldi | D25: -140 | E25: -140
B26: INSS sobre Salários - GPS | C26: Governo Federal | D26: -187.29 | E26: -187.28
B27: FGTS e Multa de FGTS | C27: Governo Federal | D27: -187.92 | E27: -187.92
B28: Materiais de Uso e Consumo | C28: SIZA DISTRIBUIDOR DE EMBALAGENS | D28: -250 | E28: -250
B29: Cursos e Treinamentos | C29: Diversos | D29: -67 | E29: -67
C30: ECC Educação | D30: -196.19 | E30: -196.19
B31: Energia Elétrica | C31: RGE/CPFL | D31: -271.64 | E31: -271.64
B32: Manutenção de Equipamentos | C32: AEL COMERCIO DE TINTAS LTDA | D32: -350 | E32: -350
B33: Viagens e Representações | C33: Diego Collaziol | D33: -400 | E33: -400
B34: Condomínio | C34: Rubi Central Towers | D34: -422.12 | E34: -422.12
B35: Simples Nacional - DAS | C35: Governo Federal | D35: -494.96 | E35: -494.96
B36: Lanches e Refeições | C36: Delícias e Sabores | D36: -109 | E36: -109
C37: Cairu | D37: -401.32 | E37: -401.32
B38: Confraternizações | C38: Confraternização | D38: -733.75 | E38: -725.04
B39: Remuneração de Estagiários | C39: RH TALENTOS AGENCIA E SERVICOS LTDA | D39: -84 | E39: -84
C40: Pedro Sella Lima | D40: -700 | E40: -700
B41: Honorários Contábeis | C41: Attivo Assessoria Contabil | D41: -800 | E41: -800
B42: Móveis, Utensílios e Instalações Administrativos | C42: Wamer Instalações Ltda (Ar condicionado) | D42: -810 | E42: -810
B43: Materiais de Limpeza e de Higiene | C43: Lourdes Terezinha Vieira Teixeira | D43: -963.33 | E43: -963.33
B44: Previdência Privada | C44: BTG Pactual Vida e Previdência | D44: -1000 | E44: -1000
B45: Bens de Pequeno Valor | C45: Ferragem Conzatti | D45: -30 | E45: -30
C46: Resimini materiais de construção | D46: -51.5 | E46: -51.5
C47: Casas Bahia | D47: -93.68 | E47: -93.68
C48: MAGAZINE LUIZA | D48: -135.48 | E48: -135.48
C49: Carrefour | D49: -399.89 | E49: -399.89
C50: Mercado Livre | D50: -717.86 | E50: -717.86
B51: Aluguel | C51: Everson Paludo | D51: -2169.95 | E51: -2019.95
B52: ISS sobre Faturamento | C52: PREFEITURA MUNICIPAL DE GARIBALDI | D52: -2283.82 | E52: -2283.82
B53: Internet e Tecnologia | C53: Canva | D53: -24.16 | E53: -24.16
C54: VIVO | D54: -33 | E54: -33
C55: Direct Call | D55: -50 | E55: -50
C56: ADYL NET TELECOM | D56: -99.9 | E56: -99.9
C57: conta Azul | D57: -247.92 | E57: -247.92
C58: OpenAI | D58: -357.43 | E58: -357.43
C59: BHS | D59: -1040.48 | E59: -1040.48
C60: RD Station | D60: -1327 | E60: -1327
B61: Marketing e Publicidade | C61: Hostinger Hospedagem | D61: -334.21 | E61: -334.21
C62: Marcelo Hensel | D62: -2025 | E62: -2025
C63: Facebook | D63: -3725.37 | E63: -3725.37
B64: Salários | C64: Danrlei Mallabarba | D64: -2000 | E64: -2000
C65: Victor De Lima Pinto | D65: -2153.08 | E65: -2153.08
C66: Anderson Cousseau | D66: -2500 | E66: -2500
B67: Pró-labore | C67: Leonardo Berteli Piveta | D67: -5000 | E67: -5000
C68: Diego Collaziol | D68: -5000 | E68: -5000
C69: Andrei Cousseau | D69: -5000 | E69: -5000
B70: Comissões de Vendedores | C70: Andrei Cousseau | D70: -200 | E70: -200
C71: RR Placas de Premiações | D71: -515 | E71: -515
C72: Victor De Lima Pinto | D72: -550 | E72: -550
C73: Daniel Louis | D73: -3792.91 | E73: -3792.91
C74: Danrlei Mallabarba | D74: -4516.35 | E74: -4516.35
C75: Anderson Lopes de Souza | D75: -5823.36 | E75: -5823.36
A76: TOTAL | D76: =SUM(D18:D75) -> 33090.75 | E76: =SUM(E18:E75) -> 33249.46
A77: Consórcios | B77: Receitas de Serviços | C77: Santander Consórcios | D77: 9678.56 | E77: 9678.56
C78: Banco BTG Pactual | D78: 1169.73 | E78: 1169.7285
B79: Impostos retidos em vendas | C79: Banco BTG Pactual | D79: 0 | E79: 0
B80: Vale-Alimentação | C80: Maicon Jonathan | D80: -54.9 | E80: -54.9
B81: Tarifas Bancárias | C81: Santander | D81: -270 | E81: -270
B82: Salários | C82: Maicon Jonathan | D82: -903.23 | E82: -903.23
B83: Comissões de Vendedores | C83: Diego Collaziol | D83: -1088 | E83: -1088
C84: Danrlei Mallabarba | D84: -1393.39 | E84: -1393.39
A85: TOTAL | D85: =SUM(D77:D84) -> 7138.77 | E85: =SUM(E77:E84) -> 7138.7685
A86: Corban | B86: Receitas de Serviços | C86: Banco BTG Pactual | D86: 5932.87 | E86: 5932.8624
B87: Impostos retidos em vendas | C87: Banco BTG Pactual | D87: 0 | E87: 0
B88: Comissões de Vendedores | C88: Anderson Lopes de Souza | D88: -37.39 | E88: -37.39
C89: Daniel Louis | D89: -189.83 | E89: -189.83
C90: Diego Collaziol | D90: -193.27 | E90: -193.27
C91: Leonardo Berteli Piveta | D91: -279.96 | E91: -279.96
C92: Andrei Cousseau | D92: -284.5 | E92: -284.5
C93: Danrlei Mallabarba | D93: -477.29 | E93: -477.29
A94: TOTAL | D94: =SUM(D86:D93) -> 4470.63 | E94: =SUM(E86:E93) -> 4470.6224
A95: Vida e Previdência | B95: Receitas de Serviços | C95: BTG Pactual Corretora de Seguros | D95: 3260.9 | E95: 3260.9
C96: FRANQ CORRETORA DE SEGUROS E PREVIDENCIA | D96: 1341.41 | E96: 1341.41
C97: BTG Pactual Vida e Previdência | D97: 4564.36 | E97: 4564.36 | F97: ok
B98: Honorários (outros) | C98: FRANQ TECNOLOGIA SA | D98: -198.66 | E98: -198.66
B99: Comissões de Vendedores | C99: Daniel Louis | D99: -10.47 | E99: -10.47
C100: Anderson Lopes de Souza | D100: -16.66 | E100: -16.66
...

Sheet Outubro
A1: Centro de custo | B1: Categoria | C1: Nome do cliente ou fornecedor | D1: Valor baixado (líquido)
A2: Robôs Quantum | B2: Receitas de Serviços | C2: Clientes Quantum | D2: 29746
B3: Tarifas | C3: LASTLINK | D3: -1794.98
B4: Devoluções por Cancelamento | C4: Clientes Quantum | D4: -1875
B5: Comissões de Vendedores | C5: Victor De Lima Pinto | D5: -231.72
C6: Diego Collaziol | D6: -231.72
C7: Daniel Louis | D7: -231.72
C8: Andrei Cousseau | D8: -239.13
C9: Anderson Lopes de Souza | D9: -278.5
C10: Danrlei Mallabarba | D10: -287.39
C11: Lucas Bavaresco | D11: -316.18
C12: Cesar Alberto Guarnieri Junior | D12: -468.52
C13: Leonardo Berteli Piveta | D13: -510.22
B14: Software / Licença de Uso | C14: JAX INVESTIMENTOS | D14: -6316.2
C15: TOTAL SAIDAS | D15: =SUM(D3:D14) -> -12781.28
C16: SALDO QUANTUM | D16: =D2+D15 -> 16964.72
A17: Consórcios | B17: Receitas de Serviços | C17: Santander Consórcios | D17: 9678.56
C18: (em branco) | D18: 3125
C19: Banco BTG Pactual | D19: 1169.731
C20: TOTAL ENTRADAS | D20: =SUM(D17:D19) -> 13973.291
B21: Impostos retidos em vendas | C21: Banco BTG Pactual | D21: 0
B22: Cursos e Treinamentos | C22: CURSOS E TREINAMENTOS EM GERAL | D22: -95
B23: Tarifas Bancárias | C23: Santander | D23: -99.9
B24: Comissões de Vendedores | C24: Maicon Jonathan | D24: -122.4
C25: Leonardo Berteli Piveta | D25: -255.39
B26: Salários | C26: Maicon Jonathan | D26: -2000
C27: TOTAL SAIDAS | D27: =SUM(D22:D26) -> -2572.69
C28: SALDO CONSORCIOS | D28: =D20+D27 -> 11400.601
A29: X10 Assessoria de Investimentos | B29: Receitas de Serviços | C29: Banco BTG Pactual | D29: 102335.69
B30: Premiações | C30: Banco BTG Pactual | D30: 7485
B31: Rendimentos de Aplicações | C31: X10 Investimentos | D31: 28.24
C32: TOTAL ENTRADAS | D32: =SUM(D29:D31) -> 109848.93
B33: Impostos retidos em vendas | C33: Banco BTG Pactual | D33: 0
B34: Exames Médicos | C34: MASTERPLAN LTDA | D34: -63.91
B35: Honorários (outros) | C35: APEME | D35: -40
C36: CIC Garibaldi | D36: -140
B37: FGTS e Multa de FGTS | C37: Governo Federal | D37: -195.45
B38: INSS sobre Salários - GPS | C38: Governo Federal | D38: -197.11
B39: Viagens e Representações | C39: Diego Collaziol | D39: -200
B40: Outras Imobilizações por Aquisição | C40: MAGAZINE LUIZA | D40: -227.16
B41: Software / Licença de Uso | C41: Mercado Livre | D41: -41.06
C42: CAPCUT | D42: -234.9
B43: Lanches e Refeições | C43: Cairu | D43: -27.98
C44: Delícias e Sabores | D44: -91.29
C45: Octavio Zandonai Cia | D45: -215.96
B46: Materiais de Uso e Consumo | C46: Anderson Cousseau | D46: -396.77
B47: Condomínio | C47: Rubi Central Towers | D47: -433.49
B48: Bens de Pequeno Valor | C48: Mercado Livre | D48: -89.07
C49: MAGAZINE LUIZA | D49: -135.48
C50: Carrefour | D50: -399.89
B51: Cursos e Treinamentos | C51: ECC Educação | D51: -196.19
C52: Morgana Stefani Mattei | D52: -460
B53: Remuneração de Estagiários | C53: RH TALENTOS AGENCIA E SERVICOS LTDA | D53: -84
C54: Pedro Sella Lima | D54: -700
B55: Honorários Contábeis | C55: Attivo Assessoria Contabil | D55: -850
B56: Materiais de Limpeza e de Higiene | C56: Lourdes Terezinha Vieira Teixeira | D56: -900
B57: Previdência Privada | C57: BTG Pactual Vida e Previdência | D57: -1000
B58: Energia Elétrica | C58: RGE/CPFL | D58: -1200.14
B59: Aluguel | C59: Everson Paludo | D59: -2019.95
B60: Compra | C60: MARCELO HENSEL AUDIOVISUAL - ME | D60: -2700
B61: Simples Nacional - DAS | C61: Governo Federal | D61: -3130.1
B62: Internet e Tecnologia | C62: Lappel Papelaria e Inf | D62: -14.5
C63: Canva | D63: -24.24
C64: VIVO | D64: -38
C65: Direct Call | D65: -50
C66: ADYL NET TELECOM | D66: -99.9
C67: conta Azul | D67: -247.92
C68: OpenAI | D68: -311.82
C69: BHS | D69: -1116
C70: RD Station | D70: -1327
B71: Marketing e Publicidade | C71: Digital Ocean | D71: -14.44
C72: Daniel Louis | D72: -691.68
C73: Facebook | D73: -2543.91
B74: ISS sobre Faturamento | C74: PREFEITURA MUNICIPAL DE GARIBALDI | D74: -3268.91
B75: Confraternizações | C75: Champagneria Garibaldi Ltda | D75: -4742
B76: Salários | C76: Danrlei Mallabarba | D76: -2000
C77: Victor De Lima Pinto | D77: -2246.05
C78: Anderson Cousseau | D78: -3500
B79: Pró-labore | C79: Leonardo Berteli Piveta | D79: -5000
C80: Diego Collaziol | D80: -5000
C81: Andrei Cousseau | D81: -5000
B82: Comissões de Vendedores | C82: Diego Collaziol | D82: -247.29
C83: Leonardo Berteli Piveta | D83: -501.54
C84: RR Placas de Premiações | D84: -585
C85: Victor De Lima Pinto | D85: -600
C86: Andrei Cousseau | D86: -1683.75
C87: Daniel Louis | D87: -4471.66
C88: Danrlei Mallabarba | D88: -7672.88
C89: Anderson Lopes de Souza | D89: -8036.33
B90: IRPJ / CSLL Trimestral | C90: Governo Federal | D90: -23814.26
C91: TOTAL SAIDAS | D91: =SUM(D34:D90) -> -101218.98
C92: SALDO X10 AAI | D92: =D32+D91 -> 8629.95
A93: Corban | B93: Receitas de Serviços | C93: Banco BTG Pactual | D93: 8224.9374
B94: Impostos retidos em vendas | C94: Banco BTG Pactual | D94: 0
B95: Comissões de Vendedores | C95: Anderson Lopes de Souza | D95: -37.78
C96: Diego Collaziol | D96: -181.44
C97: Daniel Louis | D97: -239.18
C98: Danrlei Mallabarba | D98: -285.1
C99: Leonardo Berteli Piveta | D99: -667.9
C100: Andrei Cousseau | D100: -818.04
...

Sheet Novembro
A1: Centro de custo | B1: Categoria | C1: Nome do cliente ou fornecedor | D1: Valor baixado (líquido)
A2: X10 Assessoria de Investimentos | B2: Receitas de Serviços | C2: Banco BTG Pactual | D2: 102609.64
B3: Rendimentos de Aplicações | C3: X10 Investimentos | D3: 13.53
B4: Materiais de Escritório | C4: Lappel Papelaria e Inf | D4: -29.99
B5: Exames Médicos | C5: MASTERPLAN LTDA | D5: -63.91
B6: Software / Licença de Uso | C6: SONAX | D6: -70.06
C7: Mercado Livre | D7: -82.12
B8: Honorários (outros) | C8: APEME | D8: -40
C9: CIC Garibaldi | D9: -140
B10: Móveis, Utensílios e Instalações Administrativos | C10: Ongarato Materiais Elétricos e Hidráulicos | D10: -183
B11: FGTS e Multa de FGTS | C11: Governo Federal | D11: -187.28
B12: INSS sobre Salários - GPS | C12: Governo Federal | D12: -190.4
B13: Condomínio | C13: Rubi Central Towers | D13: -407.41
B14: Energia Elétrica | C14: RGE/CPFL | D14: -415.43
B15: Lanches e Refeições | C15: Delícias e Sabores | D15: -75.03
C16: Cairu | D16: -383.13
B17: Impostos retidos em vendas | C17: Banco BTG Pactual | D17: 0
C18: MARCELO HENSEL AUDIOVISUAL - ME | D18: -486
B19: Outras Imobilizações por Aquisição | C19: MAGAZINE LUIZA | D19: -509.6
B20: Cursos e Treinamentos | C20: ECC Educação | D20: -196.19
C21: Leonardo Berteli Piveta | D21: -461.62
B22: Bens de Pequeno Valor | C22: Ferragem Conzatti | D22: -35
C23: Mercado Livre | D23: -131.65
C24: MAGAZINE LUIZA | D24: -135.48
C25: Carrefour | D25: -399.89
B26: Remuneração de Estagiários | C26: RH TALENTOS AGENCIA E SERVICOS LTDA | D26: -84
C27: Pedro Sella Lima | D27: -700
B28: Honorários Contábeis | C28: Attivo Assessoria Contabil | D28: -800
B29: Materiais de Limpeza e de Higiene | C29: Armazém da Limpeza | D29: -44.9
C30: Lourdes Terezinha Vieira Teixeira | D30: -866.8
B31: Previdência Privada | C31: BTG Pactual Vida e Previdência | D31: -1000
B32: 13º Salário - 1ª Parcela | C32: Thais da Silveira Freitas | D32: -166.67
C33: Victor De Lima Pinto | D33: -1174.76
B34: Aluguel | C34: Everson Paludo | D34: -2019.95
B35: Compra | C35: MARCELO HENSEL AUDIOVISUAL - ME | D35: -2700
B36: Internet e Tecnologia | C36: Canva | D36: -24.16
C37: VIVO | D37: -38
C38: Direct Call | D38: -50
C39: ADYL NET TELECOM | D39: -99.9
C40: conta Azul | D40: -247.92
C41: OpenAI | D41: -285.24
C42: BHS | D42: -1205.22
C43: RD Station | D43: -1465
B44: Simples Nacional - DAS | C44: Governo Federal | D44: -4107.6
B45: Marketing e Publicidade | C45: One | D45: -1
C46: Digital Ocean | D46: -43.97
C47: Daniel Louis | D47: -230.56
C48: Facebook | D48: -4556.34
B49: ISS sobre Faturamento | C49: PREFEITURA MUNICIPAL DE GARIBALDI | D49: -5115.43
B50: Salários | C50: Danrlei Mallabarba | D50: -2000
C51: Victor De Lima Pinto | D51: -2153.08
C52: Thais da Silveira Freitas | D52: -2274
C53: Anderson Cousseau | D53: -3500
B54: Pró-labore | C54: Leonardo Berteli Piveta | D54: -5000
C55: Diego Collaziol | D55: -5000
C56: Andrei Cousseau | D56: -5000
B57: Comissões de Vendedores | C57: Victor De Lima Pinto | D57: -300
C58: Morgana Stefani Mattei | D58: -676.19
C59: Daniel Louis | D59: -4482.86
C60: Anderson Lopes de Souza | D60: -5413.76
C61: Danrlei Mallabarba | D61: -6103.26
C62: TOTAL DESPESAS: | D62: =SUM(D4:D61) -> -73553.76
C63: RESULTADO FINAL: | D63: =D2+D3+D62 -> 29069.41
A64: Consórcios | B64: Receitas de Serviços | C64: Santander Consórcios | D64: 17029.44
C65: RODOBENS ADMINISTRADORA DE CON | D65: 7537.5
C66: FRANQ - FAZZ CORRETORA DE SEGUROS E PREVIDENCIA | D66: 1365.59
B67: Tarifas Bancárias | C67: Santander | D67: -109.8
B68: 13º Salário - 1ª Parcela | C68: Maicon Jonathan | D68: -333.33
B69: Salários | C69: Maicon Jonathan | D69: -2000
B70: Investimentos | C70: CONSORCIOS SERVOPA | D70: -2482.92
B71: Comissões de Vendedores | C71: Leonardo Berteli Piveta | D71: -582.25
C72: Anderson Lopes de Souza | D72: -771.63
C73: Andrei Cousseau | D73: -1542.74
C74: Diego Collaziol | D74: -2941.76
C75: Maicon Jonathan | D75: -3514.75
C76: TOTAL DESPESAS: | D76: =SUM(D67:D75) -> -14279.18
C77: RESULTADO FINAL: | D77: =D64+D65+D66+D76 -> 11653.35
A78: Robôs Quantum | B78: Receitas de Serviços | C78: Clientes Quantum | D78: 12588
B79: Tarifas | C79: LASTLINK | D79: -516.54
B80: Comissões de Vendedores | C80: Cesar Alberto Guarnieri Junior | D80: -287.39
C81: Victor De Lima Pinto | D81: -299
C82: Andrei Cousseau | D82: -661
B83: Software / Licença de Uso | C83: JAX INVESTIMENTOS | D83: -2921.7
C84: TOTAL DESPESAS: | D84: =SUM(D79:D83) -> -4685.63
C85: RESULTADO FINAL: | D85: =D78+D84 -> 7902.37
A86: Vida e Previdência | B86: Receitas de Serviços | C86: Banco BTG Pactual | D86: 4996.6099
C87: FRANQ - FAZZ CORRETORA DE SEGUROS E PREVIDENCIA | D87: 380.1
B88: Honorários (outros) | C88: FRANQ TECNOLOGIA SA | D88: -349.14
B89: Comissões de Vendedores | C89: Morgana Stefani Mattei | D89: -29.77
C90: Diego Collaziol | D90: -46
C91: Anderson Lopes de Souza | D91: -49.02
C92: Leonardo Berteli Piveta | D92: -164.57
C93: Daniel Louis | D93: -201.6
C94: Andrei Cousseau | D94: -245.87
C95: Danrlei Mallabarba | D95: -485.88
C96: TOTAL DESPESAS: | D96: =SUM(D88:D95) -> -1571.85
C97: RESULTADO FINAL: | D97: =D86+D87+D96 -> 3804.8599
A98: Corban | B98: Receitas de Serviços | C98: Banco BTG Pactual | D98: 3802.22
B99: Impostos retidos em vendas | C99: Banco BTG Pactual | D99: 0
B100: Comissões de Vendedores | C100: Morgana Stefani Mattei | D100: -50.86
...

Sheet DEZEMBRO 2025
A1: Centro de custo | B1: Categoria | C1: Descrição da parcela | D1: Valor baixado (líquido)
A2: AI Inv POA | B2: Aluguel | C2: Aluguel Poa | D2: -2804.66
B3: Bens de Pequeno Valor | C3: cadeiras Poa 4/10 | D3: -293.16
C4: Cassol compras escritório POA (xicaras etc) 2/10 | D4: -112.08
C5: Compras iniciais escritório POA (lixeira, etc) 3/8 | D5: -152.84
C6: Microondas POA 2/10 | D6: -57.67
C7: Purificado de Água POA 3/10 | D7: -69.89
C8: TV nova Escritório POA (uma compra, duas faturas) 3/10 | D8: -227.16
B9: Comissões de Vendedores | C9: COMISSÃO CORBAN LUCAS | D9: -9.21
C10: COMISSÕES V&P | D10: -17.57
C11: CORBAN CESAR | D11: -62.65
B12: Energia Elétrica | C12: ENERGIA ELETRICA ESCRITORIO POA | D12: -381.31
B13: Impostos retidos em vendas | C13: TAXA DE ABERTURA DA FILIAL DE POA | D13: -197.5
B14: Internet e Tecnologia | C14: INTERNET DA VIVO DO ESCRITORIO DE POA | D14: -208.65
B15: Móveis, Utensílios e Instalações Administrativos | C15: COMPRA DE AR CONDICIONADO PARA POA EM 8X CARTÃO DIEGO | D15: -477.38
C16: Mobiliario Porto Alegre GebWork 5/6 | D16: -2352.17
B17: Móveis, Utensílios e Instalações Comerciais | C17: 50% FINAL DOS MARMORES DE POA, DIVIDIDO EM 3 PARCELAS | D17: -950
B18: Pró-labore | C18: Pró Labore para Lucas Ogliari Bavaresco | D18: -4000
C19: Salario Cesar Alberto Guarnieri Junior | D19: -4000
B20: Receitas de Serviços | C20: RECEBIMENTO DAS COMISSÕES V & P | D20: 74.68
C21: Venda 88 (COMISSÃO AI REF NOVEMBRO 2025) | D21: 3822.2595
C22: Venda 89 (CORBAN REF NOVEMBRO 2025) | D22: 337.2094
B23: Rendimentos de Aplicações | C23: Valor de Rendimento Remunera+ | D23: 2.82
B24: Tarifas Bancárias | C24: Estorno do Valor de Rendimento | D24: -0.01
C25: RECEITA TOTAL: | D25: =SUM(D20:D24) -> 4236.9589
C26: DESPESAS TOTAL: | D26: =SUM(D2:D19) -> -16373.9
C27: SALDO FINAL: | D27: =D25+D26 -> -12136.941
A28: Consórcios | B28: Comissões de Vendedores | C28: 10% Extra de comissão sobre as vendas, por ter passado de 1M de vendas no mes de outubro (Venda do Elisael Andrade RodoBens) | D28: -191.25
C29: COMISSÃO CONSORCIOS | D29: -2286.55
C30: COMISSÕES NEWCON | D30: -255.39
C31: COMISSÕES RODOBENS | D31: -106.25
C32: COMISSÕES SERVOPA | D32: -1377.01
C33: COMISSÕS FRANQ | D33: -580.38
C34: COMISSÕS SERVOPA | D34: -860.63
C35: CONSORCIO SERVOPA | D35: -140.25
C36: SERVOPA | D36: -632.47
B37: Férias | C37: 7,5 DIAS DE FERIAS MAIS 33% | D37: -884.45
B38: Receitas de Serviços | C38: COMISSÃO RODOBENS REF NOV 2025 | D38: 625
C39: COMISSÕES DA NEWCOM DE VARIOS MESES QUE ESTAVA LIBERADO | D39: 2222.32
C40: RECEBIMENTO COMISSÕES SERVOPA ADMINISTRADORA DE CONSORCIOS LTD | D40: 18655.28
C41: RECEBIMENTO DA COMISSÃO DOS CONSORCIOS SERVOPA PRIMEIRA NOTA REF A OUTUBRO | D41: 5900
C42: RECEBIMENTO DAS COMISSÕES DOS SEGUROS FRANQ | D42: 1365.59
B43: Salários | C43: Salario Ref ao Mês Trabalhado | D43: -2000
B44: Tarifas Bancárias | C44: TARIFA MANUTENÇÃO DA CONTA | D44: -90
C45: RECEITA TOTAL: | D45: =SUM(D38:D42) -> 28768.19
C46: DESPESAS TOTAL: | D46: =SUM(D28:D37,D43,D44) -> -9404.63
C47: SALDO FINAL: | D47: =D45+D46 -> 19363.56
A48: Corban | B48: Comissões de Vendedores | C48: CORBAN | D48: -1226.92
B49: Receitas de Serviços | C49: Venda 89 (CORBAN REF NOVEMBRO 2025) | D49: 5556.9106
C50: SALDO FINAL: | D50: =D48+D49 -> 4329.9906
A51: Vida e Previdência | B51: Comissões de Vendedores | C51: V & P | D51: -1994.18
B52: Receitas de Serviços | C52: RECEBIMENTO DAS COMISSÕES V & P | D52: 6704.37
C53: SALDO FINAL: | D53: =D51+D52 -> 4710.19
A54: X10 Assessoria de Investimentos | B54: 13º Salário - 2ª Parcela | C54: SEGUNDA PARCELA DO DECIMO TERCEIRO | D54: -1142.75
B55: Aluguel | C55: Aluguel X10 Março 2025 | D55: -2019.95
B56: Bens de Pequeno Valor | C56: Ar Condicionado X10 10x 6/10 | D56: -399.89
C57: cadeiras escritório - Diego e Anderson 6/6 | D57: -135.48
C58: Cafeteira escritório GDI 3/6 | D58: -54.08
C59: Ferragem CONZATI + POSTINGHER | D59: -59.8
B60: Comissões de Vendedores | C60: COMISSÃO DE 50% DAS OFERTA BTG | D60: -703.13
C61: Comissão para Daniel Louis | D61: -3000
C62: Comissões AI | D62: -6681.97
C63: INCENTIVO ATP | D63: -2000
C64: PREMIAÇÃO 50% OFERTA BTG | D64: -43.75
C65: PREMIAÇÕES VICTOR | D65: -800
C66: SALARIO REF. AO MES TRABALHADO | D66: -3000
B67: Compra | C67: Compra de serviço Série:SN / NFS-e:2500000000763 (MENSALIDADE EXTRA ANUAL) | D67: -600
C68: Compra de serviço Série:SN / NFS-e:2500000018124 | D68: -1300.6
C69: Compra de serviço Série:SN / NFS-e:2500000075907 | D69: -34.18
C70: Compra de serviço Série:SN / NFS-e:27 (MENSALIDADE REF. A NOVEMBRO) | D70: -500
B71: Condomínio | C71: Condomínio da Sala Comercial | D71: -427.56
B72: Confraternizações | C72: JANTA DE ENCERRAMENTO DO ANO DA X10 | D72: -4539
B73: Cursos e Treinamentos | C73: 2 ENCONTROS BNI | D73: -60
C74: Curso BNI do Leo em 12x Cartão Leo | D74: -461.62
C75: Curso Consórcios 4/12 | D75: -196.19
C76: G4 PASSE VITALICIO QUE O DIEGO COMPROU EM 12X NO CARTÃO DELE | D76: -249.75
C77: PASSAGENS B2B NECTON QUE O LEO COMPROU | D77: -3251.08
B78: Energia Elétrica | C78: Energia Elétrica | D78: -335.62
B79: Exames Médicos | C79: Plano de Medicina Ocupacional | D79: -63.91
B80: Férias | C80: 18 DIAS DE FERIAS VICTOR | D80: -1739.7
C81: 24 DIAS DE FERIAS COM INICIO 23/12/2025 | D81: -560
B82: FGTS e Multa de FGTS | C82: FGTS DOS COLABORADORES PJ2 | D82: -448.97
B83: Honorários (outros) | C83: Convenio Apeme | D83: -40
C84: convenio CIC | D84: -140
B85: Honorários Contábeis | C85: HONORARIO EXTRA ANUAL | D85: -200
C86: Honorários contábeis da PJ2 | D86: -200
C87: Honorários Contabilidade | D87: -600
B88: INSS sobre Salários - GPS | C88: INSS COLABORADORES | D88: -338.82
C89: INSS DECIMO TERCEIRO | D89: -215.04
B90: Internet e Tecnologia | C90: Canva 12x 6/12 | D90: -24.24
C91: Conta Azul Anual 11/12 | D91: -247.92
C92: Direct Call (cartão Diego) | D92: -50
C93: Mensalidade do plano de Internet | D93: -99.9
C94: OPEN AI | D94: -273.86
C95: RD + RD MKT | D95: -1597
C96: Vivo | D96: -38
B97: ISS sobre Faturamento | C97: ISS sobre Faturamento | D97: -2655.21
B98: Lanches e Refeições | C98: Cairu Diversos (CARTÃO DIEGO) | D98: -385.53
C99: Delicias de Garibaldi | D99: -73.57
C100: LANCHE PARA ANIVERSARIO DIEGO (PIX VICTOR) | D100: -75.83
...

Sheet JANEIRO 2026
A1: Centro de custo | B1: Categoria | C1: Descrição da parcela | D1: Valor baixado (líquido)
A2: AI Inv POA | B2: Aluguel | C2: Aluguel Poa | D2: -2270.73
B3: Bens de Pequeno Valor | C3: cadeiras Poa 5/10 | D3: -293.16
C4: Cassol compras escritório POA (xicaras etc) 3/10 | D4: -112.08
C5: Compras iniciais escritório POA (lixeira, etc) 4/8 | D5: -152.84
C6: Microondas POA 3/10 | D6: -57.67
C7: Purificado de Água POA 4/10 | D7: -69.89
C8: TV nova Escritório POA (uma compra, duas faturas) 4/10 | D8: -227.16
B9: Comissões de Vendedores | C9: COMISSÃO CORBAN LUCAS | D9: -10.08
C10: COMISSÕES V&P | D10: -44.22
C11: CORBAN CESAR | D11: -4.14
B12: Energia Elétrica | C12: ENERGIA ELETRICA ESCRITORIO POA | D12: -370.45
B13: Internet e Tecnologia | C13: INTERNET DA VIVO DO ESCRITORIO DE POA | D13: -100.58
B14: Materiais de Limpeza e de Higiene | C14: SERVIÇO DE LIMPEZA DA SALA DE POA | D14: -180
B15: Móveis, Utensílios e Instalações Administrativos | C15: COMPRA DE AR CONDICIONADO PARA POA EM 8X CARTÃO DIEGO | D15: -477.38
C16: Mobiliario Porto Alegre GebWork 6/6 | D16: -2352.15
B17: Pró-labore | C17: Pró Labore para Lucas Ogliari Bavaresco REF. 08/2025 | D17: -4000
C18: Salario Cesar Alberto Guarnieri Junior | D18: -4000
B19: Receitas de Serviços | C19: RECEBIMENTO DAS COMISSÕES V & P | D19: 221.0996
C20: Venda 92 (COMISSÃO AI ) | D20: 4067.15
C21: Venda 93 (CORBAN) | D21: 71.0598
B22: Rendimentos de Aplicações | C22: Valor de Rendimento Remunera+ | D22: 0.88
C23: RECEITA TOTAL: | D23: =D19+D20+D21+D22 -> 4360.1894
C24: DESPESAS TOTAL: | D24: =D2+D3+D4+D5+D6+D7+D8+D9+D10+D11+D12+D13+D14+D15+D16+D17+D18 -> -14722.53
C25: SALDO FINAL: | D25: =D23+D24 -> -10362.341
A26: Consórcios | B26: Comissões de Vendedores | C26: COMISSÕES RODOBENS | D26: -153
C27: COMISSÕES SERVOPA | D27: -97.75
C28: COMISSÕS FRANQ | D28: -580.38
C29: COMISSÕS SERVOPA | D29: -153
C30: CONSORCIOS SERVOPA | D30: -141.6
C31: PREMIAÇÃO POR TER CHEGO EM 3 MILHOES DE CONSORCIO EM 2025 | D31: -1000
B32: Investimentos | C32: 9 CARTAS DE CONSORCIOS DE 110 MIL CADA UMA | D32: -2483.91
B33: Receitas de Serviços | C33: COMISSÃO DAS VENDAS DOS CONSORCIOS SERVOPA | D33: 1730.28
C34: COMISSÕES RECEBIDAS DA FRANQ TECNOLOGIA SA | D34: 1365.59
C35: RECEBIMENTO DAS COMISSÕES RODOBENS | D35: 1350
B36: Salários | C36: Salario Ref 18 Dias Trabalhados em Dezembro | D36: -1162
B37: Tarifas Bancárias | C37: Tarifa Manutencao Conta Corrente 23/01/2026 | D37: -99
C38: RECEITA TOTAL: | D38: =D33+D34+D35 -> 4445.87
C39: DESPESAS TOTAL: | D39: =D26+D27+D28+D29+D30+D31+D32+D36+D37 -> -5870.64
C40: SALDO FINAL: | D40: =D38+D39 -> -1424.77
A41: Corban | B41: Comissões de Vendedores | C41: CORBAN | D41: -1196.08
C42: FINANCIAMENTO VENDIDO PELA FRANQ | D42: -2543.63
B43: Impostos retidos em vendas | C43: Venda 93 (CORBAN) | D43: -279.4093
B44: Receitas de Serviços | C44: COMISSÕES RECEBIDAS DA FRANQ TECNOLOGIA SA | D44: 5985
C45: Venda 93 (CORBAN) | D45: 4472.3795
C46: RECEITA TOTAL: | D46: =D44+D45 -> 10457.379
C47: DESPESAS TOTAL: | D47: =D41+D42+D43 -> -4019.1193
C48: SALDO FINAL: | D48: =D46+D47 -> 6438.2602
A49: Vida e Previdência | B49: Comissões de Vendedores | C49: V & P | D49: -1242.14
B50: Honorários (outros) | C50: Royalties pagos a Franq | D50: -273.12
B51: Receitas de Serviços | C51: RECEBIMENTO DAS COMISSÕES V & P | D51: 5024.3604
C52: RECEITA TOTAL: | D52: =D51 -> 5024.3604
C53: DESPESAS TOTAL: | D53: =SUM(D49:D50) -> -1515.26
C54: SALDO FINAL: | D54: =D52+D53 -> 3509.1004
A55: X10 Assessoria de Investimentos | B55: Aluguel | C55: Aluguel X10 Março 2025 | D55: -2019.95
B56: Bens de Pequeno Valor | C56: Ar Condicionado X10 10x 7/10 | D56: -399.89
C57: Cafeteira escritório GDI 4/6 | D57: -54.08
B58: Comissões de Vendedores | C58: Comissões AI | D58: -12552.56
C59: INCENTIVO ATP SERIA 2 MIL A ULTIMA PARCELA, MAS FOI DESCONTADO 1500 REF AOS 15% DE IMPOSTO | D59: -500
C60: PREMIAÇÃO POR TER FICADO EM PRIMEIRO EM NNM EM DEZEMBRO, CESTA DE FINAL DE ANO | D60: -600
C61: PREMIAÇÃO POR TER FICADO EM SEGUNDO EM NNM EM DEZEMBRO, CESTA DE FINAL DE ANO | D61: -400
C62: PREMIAÇÕES VICTOR | D62: -500
B63: Compra | C63: Compra de serviço Série:1 / NFS-e:1515 (SONAX) | D63: -21.32
C64: Compra de serviço Série:1 / NFS-e:2079543 (PASTAS PROPOSTA E FRETE) | D64: -444.57
C65: Compra de serviço Série:1 / NFS-e:6199 (Attivo) | D65: -600
C66: Compra de serviço Série:54345 / NFS-e:104284 (BHS EMAILS CORPORATIVOS) | D66: -1300.6
C67: Compra de serviço Série:SN / NFS-e:196 | D67: -500
C68: Compra de serviço Série:SN / NFS-e:7218 (RS STATION) | D68: -1189.26
B69: Condomínio | C69: Condomínio da Sala Comercial | D69: -412.19
B70: Confraternizações | C70: PRESENTES FINAL DE ANO PARA COLABORADORES | D70: -509.55
C71: PRESENTES PARA FINAL DE ANO DOS COLABORADORES (JAVY + CUBO GRAFICA + CASA DEL GRANI + APP) | D71: -626.37
B72: Cursos e Treinamentos | C72: CONSULTORIA EMPRESARIA PARA 2026 | D72: -3000
C73: Curso BNI do Leo em 12x Cartão Leo | D73: -461.62
C74: Curso Consórcios 5/12 | D74: -196.19
C75: G4 PASSE VITALICIO QUE O DIEGO COMPROU EM 12X NO CARTÃO DELE | D75: -249.75
B76: Energia Elétrica | C76: Energia Elétrica | D76: -413.24
B77: Exames Médicos | C77: Plano de Medicina Ocupacional | D77: -63.91
B78: FGTS e Multa de FGTS | C78: FGTS DECIMO TERCEIRO | D78: -108.61
C79: FGTS DOS COLABORADORES PJ2 | D79: -376.62
C80: FGTS RESCISÃO THAIS | D80: -11.24
C81: PARCELA DO FGTS QUE NÃO FOI PAGA QUANDO ESTAVA SEM CARTEIRA E ELA COBROU ISSO | D81: -160
B82: Honorários (outros) | C82: Convenio Apeme | D82: -40
C83: convenio CIC | D83: -150
B84: Honorários Contábeis | C84: Honorários contábeis da PJ2 | D84: -200
B85: Impostos retidos em vendas | C85: Venda 92 (COMISSÃO AI ) | D85: -4709.87
B86: INSS sobre Salários - GPS | C86: INSS COLABORADORES | D86: -378.16
B87: Internet e Tecnologia | C87: Canva 12x 7/12 | D87: -24.24
C88: Conta Azul Anual 12/12 | D88: -247.92
C89: Direct Call (cartão Diego) | D89: -50
C90: Mensalidade do plano de Internet | D90: -99.9
C91: OPEN AI | D91: -233.07
C92: RD MKT | D92: -607
C93: Vivo | D93: -38
B94: IRPJ / CSLL Trimestral | C94: IRPJ QUARTO TRIMESTRE | D94: -26370.68
B95: ISS sobre Faturamento | C95: ISS sobre Faturamento | D95: -3524.65
B96: Marketing e Publicidade | C96: BNI Daniel Turma Bento 12x | D96: -691.68
C97: ENTRADA DE 50% PARA DESENVOLVIMENTO DO NOVO SITE | D97: -900
C98: Facebook | D98: -2938.88
C99: INVESTIMENTO EM GOOGLE E YOUTUBE ANDREI | D99: -415.47
C100: Videos mkt institucional | D100: -2700
...

Sheet FEVEREIRO 2026
A1: Centro de custo | B1: Categoria | C1: Descrição da parcela | D1: Valor baixado (líquido)
A2: AI Inv POA | B2: Aluguel | C2: Aluguel POA | D2: -2308.9
B3: Bens de Pequeno Valor | C3: cadeiras Poa 6/10 | D3: -293.16
C4: Compras iniciais escritório POA (lixeira, etc) 5/8 | D4: -152.84
C5: Microondas POA 4/10 | D5: -57.67
C6: Purificado de Água POA 5/10 | D6: -69.89
C7: TV nova Escritório POA (uma compra, duas faturas) 5/10 | D7: -227.16
B8: Comissões de Vendedores | C8: COMISSÃO CORBAN LUCAS | D8: -81.14
C9: COMISSÃO RODOBENS LUCAS | D9: -178.5
C10: COMISSÕES V&P | D10: -42.74
C11: CORBAN CESAR | D11: -29.44
B12: Cursos e Treinamentos | C12: HOSPEDAGEM DA EQUIPE GDI EM SÃO PAULO NO EVENTO BTG | D12: -676.3
C13: HOSPEDAGEM LUCAS E CESAR EM SÃO PAULO NO EVENTO BTG | D13: -225.43
C14: JANTA EM SÃO PAULO EVENTO BTG CESAR E LUCAS | D14: -84.56
C15: JANTA EM SÃO PAULO EVENTO BTG PARA TODA EQUIPE GDI | D15: -210.44
B16: Energia Elétrica | C16: ENERGIA ELETRICA ESCRITORIO POA | D16: -103.4
B17: Internet e Tecnologia | C17: INTERNET DA VIVO DO ESCRITORIO DE POA | D17: -102.04
B18: Móveis, Utensílios e Instalações Administrativos | C18: COMPRA DE AR CONDICIONADO PARA POA EM 8X CARTÃO DIEGO | D18: -477.38
B19: Pró-labore | C19: Pró Labore para Lucas Ogliari Bavaresco REF. 08/2025 | D19: -4000
C20: Salario Cesar Alberto Guarnieri Junior | D20: -4000
B21: Receitas de Serviços | C21: COMISSÃO DA VENDA DOS CONSORCIOS RODOBENS | D21: 758.63
C22: COMISSÕES V&P | D22: 181.64
C23: Venda 95 (COMISSÃO AI) | D23: 10276.67
C24: Venda 96 (CORBAN DESCONTADO CANCELAMENTO CONSORCIO ANDERSOL LOPES) | D24: 470
B25: Rendimentos de Aplicações | C25: Valor de Rendimento Remunera+ | D25: 16.63
C26: RECEITA TOTAL: | D26: =SUM(D21:D25) -> 11703.57
C27: DESPESAS TOTAL: | D27: =SUM(D2:D20) -> -13320.99
C28: SALDO FINAL: | D28: =D26+D27 -> -1617.42
A29: Consórcios | B29: Comissões de Vendedores | C29: COMISSÃO CONSORCIOS DAS VENDAS FEITAS E GERADAS PELO MAICON, 2 PARCELAS MATHEUS CORREA E 1 PARCELA MISAEL | D29: -198.9
C30: COMISSÃO CONSORCIOS SERVOPA | D30: -544
C31: COMISSÕES SERVOPA | D31: -420.76
C32: COMISSÕS FRANQ | D32: -580.38
C33: COMISSÕS SERVOPA | D33: -76.5
C34: CONSORCIO SERVOPA | D34: -70.13
B35: Cursos e Treinamentos | C35: Curso Consórcios 6/12 | D35: -196.19
B36: Investimentos | C36: 9 CARTAS DE CONSORCIOS DE 110 MIL CADA UMA | D36: -2483.91
B37: Receitas de Serviços | C37: COMISSÃO DA VENDA DOS CONSORCIOS RODOBENS | D37: 291.37
C38: COMISSÕES RECEBIDAS DA FRANQ | D38: 1365.59
C39: COMISSÕES SERVOPA | D39: 7200
C40: RECEBIDO COMISSÃO NEWCOM | D40: 480
B41: Tarifas Bancárias | C41: Tarifa Manutencao Conta Corrente 23/02/2026 | D41: -99
C42: RECEITA TOTAL: | D42: =SUM(D37:D40) -> 9336.96
C43: DESPESAS TOTAL: | D43: =SUM(D29:D36)+D41 -> -4669.77
C44: SALDO FINAL: | D44: =D42+D43 -> 4667.19
A45: Corban | B45: Comissões de Vendedores | C45: CORBAN | D45: -2362.67
B46: Honorários (outros) | C46: ROYALTIES SOBRE AS VENDAS DO MES, MAIOR VENDA FOI DO FINANCIAMENTO VENDIDO PELO DANRLEI | D46: -1470.12
B47: Impostos retidos em vendas | C47: Venda 96 (CORBAN DESCONTADO CANCELAMENTO CONSORCIO ANDERSOL LOPES) | D47: -86.52
B48: Receitas de Serviços | C48: Venda 96 (CORBAN DESCONTADO CANCELAMENTO CONSORCIO ANDERSOL LOPES) | D48: 936.84
C49: RECEITA TOTAL: | D49: =D48 -> 936.84
C50: DESPESAS TOTAL: | D50: =SUM(D45:D47) -> -3919.31
C51: SALDO FINAL: | D51: =D49+D50 -> -2982.47
A52: Vida e Previdência | B52: Comissões de Vendedores | C52: V & P | D52: -2240.85
C53: V & P + 2 MESES JOSI QUE ESTAVA FORA SISTEMA | D53: -255.87
B54: Honorários (outros) | C54: Royalties pagos a Franq | D54: -273.12
B55: Receitas de Serviços | C55: COMISSÕES V&P | D55: 11290.9
C56: RECEITA TOTAL: | D56: =D55 -> 11290.9
C57: DESPESAS TOTAL: | D57: =SUM(D52:D54) -> -2769.84
C58: SALDO FINAL: | D58: =D56+D57 -> 8521.06
A59: X10 Assessoria de Investimentos | B59: Aluguel | C59: Aluguel X10 Março 2025 | D59: -2019.95
B60: Bens de Pequeno Valor | C60: Ar Condicionado X10 10x 8/10 | D60: -399.89
C61: Cafeteira escritório GDI 5/6 | D61: -54.08
B62: Comissões de Vendedores | C62: Comissões AI | D62: -24546.8
C63: PREMIAÇÃO DE 300,00 POR CAPTAR 1 M EM JANEIRO e POR TER BATIDO A META PESSOAL DE 1.5 MILHOES | D63: -600
C64: PREMIAÇÃO PELAS METAS BATIDAS DO ESCRITORIO NO ANO DE 2025 | D64: -24999.99
C65: PREMIAÇÕES VICTOR | D65: -600
C66: PREMIO 300 META 1 M, 300 META DO MES, 200 PRIMEIRO RANKING, 500, 2 MILHOES | D66: -1300
C67: PREMIO 300 META 1 MILHÃO DE CAPTAÇÃO , 300 META DO MES | D67: -600
B68: Compra | C68: Compra de serviço Série:00900 / NFS-e:396 (AWZ) | D68: -500
C69: Compra de serviço Série:1 / NFS-e:6364 (ATTIVO) | D69: -650
C70: Compra de serviço Série:3 / NFS-e:152610 RD Stantin | D70: -1190
C71: Compra de serviço Série:3000 / NFS-e:2746704 CONTA AZUL EM 12X CARTÃO DIEGO 1/12 | D71: -257.87
C72: Compra de serviço Série:49999 / NFS-e:6 (ALTERAÇÕES CONTRATUAIS E ABERTURA FILIAL POA) | D72: -1400
C73: Compra de serviço Série:54345 / NFS-e:105709 (BHS EMAILS) | D73: -1300.6
C74: Compra de serviço Série:900 / NFS-e:13 | D74: -84
B75: Condomínio | C75: Condomínio da Sala Comercial | D75: -448.25
B76: Cursos e Treinamentos | C76: 2 CAFES NO BNI JANEIRO 150 E FEVEREIRO 180 MAIS ESTACIONAMENTO IDA A SÃO PAULO 155,00 | D76: -485
C77: CONSULTORIA EMPRESARIA PARA 2026 | D77: -3000
C78: Curso BNI do Leo em 12x Cartão Leo | D78: -461.62
C79: CUSTOS CARRO ANDREI ATE AEROPORTO PARA IR A SP 250,00 MAIS UBER SP | D79: -536.84
C80: G4 PASSE VITALICIO QUE O DIEGO COMPROU EM 12X NO CARTÃO DELE | D80: -249.75
C81: HOSPEDAGEM DA EQUIPE GDI EM SÃO PAULO NO EVENTO BTG | D81: -2028.87
C82: HOSPEDAGEM LUCAS E CESAR EM SÃO PAULO NO EVENTO BTG | D82: -676.3
C83: JANTA EM SÃO PAULO EVENTO BTG CESAR E LUCAS | D83: -210.44
C84: JANTA EM SÃO PAULO EVENTO BTG PARA TODA EQUIPE GDI | D84: -523.72
B85: Descontos incondicionais obtidos | C85: RESTITUIÇÃO DE IMPOSTOS PAGOS DE NOTAS CANCELADAS | D85: 554.07
B86: Energia Elétrica | C86: Energia Elétrica | D86: -515.13
B87: Exames Médicos | C87: Plano de Medicina Ocupacional | D87: -63.91
B88: FGTS e Multa de FGTS | C88: FGTS DOS COLABORADORES PJ2 | D88: -196.02
B89: Honorários (outros) | C89: Convenio Apeme + Custos com evento do Diego | D89: -115
C90: convenio CIC | D90: -150
B91: Honorários Contábeis | C91: Honorários contábeis da PJ2 | D91: -200
B92: Impostos retidos em vendas | C92: Venda 94 (ATP ANDERSON SOUZA TARGET 1 ) | D92: -615
C93: Venda 95 (COMISSÃO AI) | D93: -8351.32
B94: INSS sobre Salários - GPS | C94: INSS COLABORADORES | D94: -206.2
B95: Internet e Tecnologia | C95: Canva 12x 8/12 | D95: -24.24
C96: Direct Call (cartão Diego) | D96: -50
C97: Mensalidade do plano de Internet | D97: -99.9
C98: OPEN AI | D98: -226.43
C99: RD MKT | D99: -607
C100: Vivo | D100: -38
...

Sheet MARÇO 2026
A1: Centro de custo | B1: Categoria | C1: Descrição da parcela | D1: Valor baixado (líquido)
A2: AI Inv POA | B2: Aluguel | C2: Aluguel Poa | D2: -2734.07
B3: Bens de Pequeno Valor | C3: cadeiras Poa 7/10 | D3: -293.16
C4: Compras iniciais escritório POA (lixeira, etc) 6/8 | D4: -152.84
C5: Microondas POA 5/10 | D5: -57.67
C6: Purificado de Água POA 6/10 | D6: -69.89
C7: TV nova Escritório POA (uma compra, duas faturas) 6/10 | D7: -227.16
B8: Comissões de Vendedores | C8: COMISSÃO CORBAN LUCAS | D8: -128.59
C9: COMISSÕES V&P | D9: -40.76
C10: CORBAN CESAR | D10: -24.27
B11: Compra | C11: Compra de produto Série:3 / NFS-e:352311 | D11: -335.65
B12: Cursos e Treinamentos | C12: CUSTOS NO CARTÃO DIEGO IDA A SP, UBER, ESTACIONAMENTO AEROPORTO E IDA DE GDI A POA COM CARRO | D12: -144
B13: Energia Elétrica | C13: ENERGIA ELETRICA ESCRITORIO POA | D13: -389.18
B14: Internet e Tecnologia | C14: INTERNET DA VIVO DO ESCRITORIO DE POA | D14: -99.99
B15: Marketing e Publicidade | C15: Facebook | D15: -678
B16: Materiais de Uso e Consumo | C16: COMPRAS GERAIS PARA ESCRITORIO POA, CAFE, PANO ETC | D16: -99.24
B17: Móveis, Utensílios e Instalações Administrativos | C17: COMPRA DE AR CONDICIONADO PARA POA EM 8X CARTÃO DIEGO | D17: -477.24
B18: Pró-labore | C18: Pró Labore Lucas Ogliari Bavaresco | D18: -4000
C19: Pró Labore Cesar Alberto Guarnieri Junior | D19: -4000
B20: Receitas de Serviços | C20: RECEBIMENTO DAS COMISSÕES V & P | D20: 203.79
C21: Venda 100(COMISSÃO AI) | D21: 2740.35
C22: Venda 99 (CORBAN) | D22: 764.3179
B23: Rendimentos de Aplicações | C23: Valor de Rendimento Remunera+ | D23: 15.35
C24: RECEITA TOTAL: | D24: =SUM(D20:D23) -> 3723.8079
C25: DESPESAS TOTAL: | D25: =SUM(D2:D19) -> -13951.71
C26: SALDO FINAL: | D26: =D24+D25 -> -10227.902
A27: Consórcios | B27: Comissões de Vendedores | C27: COMISSÃO RODOBENS | D27: -706.56
C28: COMISSÕES SERVOPA | D28: -1190.01
C29: COMISSÕS FRANQ | D29: -738.75
C30: COMISSÕS SERVOPA | D30: -541.88
C31: CONSORCIO SERVOPA | D31: -140.25
B32: Cursos e Treinamentos | C32: Curso Consórcios 7/12 | D32: -196.19
B33: Investimentos | C33: 9 CARTAS DE CONSORCIOS DE 110 MIL CADA UMA | D33: -2483.91
B34: Materiais de Uso e Consumo | C34: COMPRA DE CHIP DA VIVO PARA SETOR DE CONSORCIOS | D34: -30.9
B35: Receitas de Serviços | C35: COMISSÃO NEWCOM | D35: 240
C36: COMISSOES FRANQ | D36: 2172.79
C37: COMISSOES RODOBENS | D37: 1662.5
C38: COMISSOES SERVOPA | D38: 8850
B39: Tarifas Bancárias | C39: Tarifa Manutencao Conta Corrente 23/03/2026 | D39: -99
C40: RECEITA TOTAL: | D40: =SUM(D35:D38) -> 12925.29
C41: DESPESAS TOTAL: | D41: =SUM(D27:D34)+D39 -> -6127.45
C42: SALDO FINAL: | D42: =D40+D41 -> 6797.84
A43: Corban | B43: Comissões de Vendedores | C43: CORBAN | D43: -1713.59
B44: Impostos retidos em vendas | C44: Venda 99 (CORBAN) | D44: -486.5587
B45: Receitas de Serviços | C45: Venda 99 (CORBAN) | D45: 7147.4808
C46: RECEITA TOTAL: | D46: =SUM(D45) -> 7147.4808
C47: DESPESAS TOTAL: | D47: =SUM(D43:D44) -> -2200.1487
C48: SALDO FINAL: | D48: =D46+D47 -> 4947.3321
A49: Imobiliário | B49: Comissões de Vendedores | C49: COMISSÕES PATAMAR | D49: -3187.5
B50: Receitas de Serviços | C50: COMISSÕES DE 3 VENDAS DA PATAMAR | D50: 7500
C51: RECEBIMENTO DA COMISSÃO PATAMAR | D51: 2500
C52: RECEITA TOTAL: | D52: =SUM(D50:D51) -> 10000
C53: DESPESAS TOTAL: | D53: =SUM(D49) -> -3187.5
C54: SALDO FINAL: | D54: =D52+D53 -> 6812.5
A55: Vida e Previdência | B55: Comissões de Vendedores | C55: V & P | D55: -2924.11
B56: Receitas de Serviços | C56: RECEBIMENTO DAS COMISSÕES V & P | D56: 9240.93
C57: RECEITA TOTAL: | D57: =SUM(D56) -> 9240.93
C58: DESPESAS TOTAL: | D58: =SUM(D55) -> -2924.11
C59: SALDO FINAL: | D59: =D57+D58 -> 6316.82
A60: X10 Assessoria de Investimentos | B60: Aluguel | C60: Aluguel X10 Março 2025 | D60: -2019.95
B61: Bens de Pequeno Valor | C61: Ar Condicionado X10 10x 9/10 | D61: -399.89
C62: Cafeteira escritório GDI 6/6 | D62: -54.08
B63: Comissões de Vendedores | C63: Comissões AI | D63: -10804.31
C64: COMISSÕES AI DIEGO | D64: -1061.71
C65: COMISSÕES GESTÃO PATRIMONIAL DIEGO | D65: -1078.96
C66: COMPLEMENTO DE SALARIO MINIMO | D66: -845.53
C67: MINIMO GARANTIDO | D67: -3000
C68: PREMIAÇÃO DA RECEITA EXCEDENTE GERADA NO TRIMESTRE ACIMA DE 30 MIL | D68: -7555.42
C69: PREMIAÇÕES VICTOR | D69: -600
C70: PREMIO POR BATER META INDIVIDUAL EM FEVEREIRO, CAPTAR MAIS QUE 1 MILHAO E MAIS QUE 2 MILHOES | D70: -900
B71: Compra | C71: Compra de produto Série:3 / NFS-e:352311 | D71: -1342.6
C72: Compra de serviço Série:002 / NFS-e:783 (BOLETO VEIO COM VALOR DIFERENTE DA NOTA, 1300,60 | D72: -1300.6
C73: Compra de serviço Série:00900 / NFS-e:461 | D73: -500
C74: Compra de serviço Série:1 / NFS-e:6534 | D74: -650
C75: Compra de serviço Série:3000 / NFS-e:2746704 CONTA AZUL EM 12X CARTÃO DIEGO 2/12 | D75: -257.87
C76: Compra de serviço Série:70000 / NFS-e:6 (ESTAGIO PEDRO) | D76: -84
B77: Condomínio | C77: Condomínio da Sala Comercial | D77: -432.29
B78: Cursos e Treinamentos | C78: 4 CAFES NO BNI MARÇO | D78: -300
C79: CONSULTORIA EMPRESARIA PARA 2026 | D79: -3000
C80: Curso BNI do Leo em 12x Cartão Leo | D80: -461.62
C81: CUSTOS NO CARTÃO DIEGO IDA A SP, UBER, ESTACIONAMENTO AEROPORTO E IDA DE GDI A POA COM CARRO | D81: -571.48
C82: G4 PASSE VITALICIO QUE O DIEGO COMPROU EM 12X NO CARTÃO DELE | D82: -249.75
B83: Energia Elétrica | C83: Energia Elétrica | D83: -725.96
B84: Exames Médicos | C84: Plano de Medicina Ocupacional | D84: -63.91
B85: FGTS e Multa de FGTS | C85: FGTS DOS COLABORADORES PJ2 | D85: -203.28
B86: Honorários (outros) | C86: Convenio Apeme | D86: -40
C87: convenio CIC | D87: -150
B88: Honorários Contábeis | C88: Honorários contábeis da PJ2 | D88: -200
B89: Impostos retidos em vendas | C89: Venda 100(COMISSÃO AI | D89: -3950.96
B90: INSS sobre Salários - GPS | C90: INSS COLABORADORES | D90: -204.37
B91: Internet e Tecnologia | C91: Canva 12x 9/12 | D91: -24.24
C92: Direct Call (cartão Diego) | D92: -50
C93: Mensalidade do plano de Internet | D93: -99.9
C94: OPEN AI | D94: -230.68
C95: RD MKT | D95: -607.04
C96: Vivo | D96: -38
B97: ISS sobre Faturamento | C97: ISS sobre Faturamento | D97: -4116.02
B98: Lanches e Refeições | C98: COMPRAS NO MES NA PADARIA | D98: -62.3
B99: Marketing e Publicidade | C99: ANUNCIOS FACE NO CARTÃO DO ANDREI PELA CONTA DE ANUNCIOS ENTRE ALTAS E BAIXAS | D99: -1436.34
C100: AUTOMAÇÃO LINKEDIN PARA CAPTAR ASSESSORES | D100: -449.9
...

Sheet 2025 Centro de Custos
A1: Fechamento de Mês
B2: 45658 | C2: 45689 | D2: 45717 | E2: 45748 | F2: 45778 | G2: 45809 | H2: 45839 | I2: 45870 | L2: 45901 | O2: 45931 | R2: 45962 | U2: 45992 | X2: 46023 | AA2: 46054 | AD2: 46082
I3: Faturamento | J3: Despesas | K3: Saldo | L3: Faturamento | M3: Despesas | N3: Saldo | O3: Faturamento | P3: Despesas | Q3: Saldo | R3: Faturamento | S3: Despesas | T3: Saldo | U3: Faturamento | V3: Despesas | W3: Saldo | X3: Faturamento | Y3: Despesas | Z3: Saldo | AA3: Faturamento | AB3: Despesas | AC3: Saldo | AD3: Faturamento | AE3: Despesas | AF3: Saldo
A4: X10 AI | B4: 54627.08 | I4: 79014.15 | J4: 77241.65 | K4: =I4-J4 -> 1772.5 | L4: 94011.48 | M4: 60839.02 | N4: =L4-M4 -> 33172.46 | O4: 109848.93 | P4: 101218.98 | Q4: =O4-P4 -> 8629.95 | R4: 102623.17 | S4: 73553.76 | T4: =R4-S4 -> 29069.41 | U4: 100569.97 | V4: 83389.14 | W4: =U4-V4 -> 17180.83 | X4: ='JANEIRO 2026'!D125 -> 73071.73 | Y4: ='JANEIRO 2026'!D126 -> -103596.29 | Z4: =X4+Y4 -> -30524.56 | AA4: ='FEVEREIRO 2026'!D126 -> 137121.34 | AB4: ='FEVEREIRO 2026'!D127 -> -118501.77 | AC4: =AA4+AB4 -> 18619.57 | AD4: =68660.73+2.62 -> 68663.35 | AE4: ='MARÇO 2026'!D128 -> -83836.46 | AF4: =AD4+AE4 -> -15173.11
A5: Consórcios | B5: 3625.8 | K5: =I5-J5 -> 0 | L5: 10848.29 | M5: 3709.52 | N5: =L5-M5 -> 7138.77 | O5: 13973.29 | P5: 2572.69 | Q5: =O5-P5 -> 11400.6 | R5: 25932.53 | S5: 14279.18 | T5: =R5-S5 -> 11653.35 | U5: 28768.19 | V5: 9404.63 | W5: =U5-V5 -> 19363.56 | X5: ='JANEIRO 2026'!D38 -> 4445.87 | Y5: ='JANEIRO 2026'!D39 -> -5870.64 | Z5: =X5+Y5 -> -1424.77 | AA5: ='FEVEREIRO 2026'!D42 -> 9336.96 | AB5: ='FEVEREIRO 2026'!D43 -> -4669.77 | AC5: =AA5+AB5 -> 4667.19 | AD5: 12925.29 | AE5: ='MARÇO 2026'!D41 -> -6127.45 | AF5: =AD5+AE5 -> 6797.84
A6: Corban | B6: 1653.0075 | K6: =I6-J6 -> 0 | L6: 5932.87 | M6: 1462.24 | N6: =L6-M6 -> 4470.63 | O6: 8224.94 | P6: 2229.44 | Q6: =O6-P6 -> 5995.5 | R6: 3802.22 | S6: 2688.2 | T6: =R6-S6 -> 1114.02 | U6: 5556.91 | V6: 1226.92 | W6: =U6-V6 -> 4329.99 | X6: ='JANEIRO 2026'!D46 -> 10457.379 | Y6: ='JANEIRO 2026'!D47 -> -4019.1193 | Z6: =X6+Y6 -> 6438.2602 | AA6: ='FEVEREIRO 2026'!D49 -> 936.84 | AB6: ='FEVEREIRO 2026'!D50 -> -3919.31 | AC6: =AA6+AB6 -> -2982.47 | AD6: 7147.5 | AE6: ='MARÇO 2026'!D47 -> -2200.1487 | AF6: =AD6+AE6 -> 4947.3513
A7: V&P | B7: 39340.615 | J7: 69.63 | K7: =I7-J7 -> -69.63 | L7: 9166.67 | M7: 1977.16 | N7: =L7-M7 -> 7189.51 | O7: 4799.96 | P7: 1453.42 | Q7: =O7-P7 -> 3346.54 | R7: 5376.71 | S7: 1571.85 | T7: =R7-S7 -> 3804.86 | U7: 6704.37 | V7: 1994.18 | W7: =U7-V7 -> 4710.19 | X7: ='JANEIRO 2026'!D52 -> 5024.3604 | Y7: ='JANEIRO 2026'!D53 -> -1515.26 | Z7: =X7+Y7 -> 3509.1004 | AA7: ='FEVEREIRO 2026'!D56 -> 11290.9 | AB7: ='FEVEREIRO 2026'!D57 -> -2769.84 | AC7: =AA7+AB7 -> 8521.06 | AD7: 9240.93 | AE7: ='MARÇO 2026'!D58 -> -2924.11 | AF7: =AD7+AE7 -> 6316.82
A8: POA | I8: 3429.73 | J8: 42060.88 | K8: =I8-J8 -> -38631.15 | L8: 1189.3 | M8: 18129.05 | N8: =L8-M8 -> -16939.75 | O8: 3142.59 | P8: 16517.76 | Q8: =O8-P8 -> -13375.17 | R8: 9642.08 | S8: 18968.1 | T8: =R8-S8 -> -9326.02 | U8: 4236.96 | V8: 16373.9 | W8: =U8-V8 -> -12136.94 | X8: ='JANEIRO 2026'!D23 -> 4360.1894 | Y8: ='JANEIRO 2026'!D24 -> -14722.53 | Z8: =X8+Y8 -> -10362.341 | AA8: ='FEVEREIRO 2026'!D26 -> 11703.57 | AB8: ='FEVEREIRO 2026'!D27 -> -13320.99 | AC8: =AA8+AB8 -> -1617.42 | AD8: =3708.46+15.35 -> 3723.81 | AE8: ='MARÇO 2026'!D25 -> -13951.71 | AF8: =AD8+AE8 -> -10227.9
A9: Imobiliario | J9: 255 | K9: =I9-J9 -> -255 | N9: =L9-M9 -> 0 | O9: 3300 | P9: 790.5 | Q9: =O9-P9 -> 2509.5 | T9: =R9-S9 -> 0 | W9: =U9-V9 -> 0 | Z9: =X9-Y9 -> 0 | AC9: =AA9-AB9 -> 0 | AD9: 10000 | AE9: ='MARÇO 2026'!D53 -> -3187.5 | AF9: =AD9-AE9 -> 13187.5
A10: QUANTUM | I10: 78172.8 | J10: 15454.4 | K10: =I10-J10 -> 62718.4 | L10: 139680.58 | M10: 53831.46 | N10: =L10-M10 -> 85849.12 | O10: 29746 | P10: 12781.28 | Q10: =O10-P10 -> 16964.72 | R10: 12588 | S10: 4685.63 | T10: =R10-S10 -> 7902.37 | W10: =U10-V10 -> 0 | Z10: =X10-Y10 -> 0 | AC10: =AA10-AB10 -> 0 | AF10: =AD10-AE10 -> 0
A11: Bonus Incentivo | K11: =I11-J11 -> 0 | N11: =L11-M11 -> 0 | Q11: =O11-P11 -> 0 | T11: =R11-S11 -> 0 | W11: =U11-V11 -> 0 | Z11: =X11-Y11 -> 0 | AC11: =AA11-AB11 -> 0 | AF11: =AD11-AE11 -> 0
A12: CAPTAL | K12: =I12-J12 -> 0 | N12: =L12-M12 -> 0 | Q12: =O12-P12 -> 0 | T12: =R12-S12 -> 0 | W12: =U12-V12 -> 0 | Z12: =X12-Y12 -> 0 | AC12: =AA12-AB12 -> 0 | AF12: =AD12-AE12 -> 0
A13: ÂNCORA | B13: 751.16 | K13: =I13-J13 -> 0 | N13: =L13-M13 -> 0 | Q13: =O13-P13 -> 0 | T13: =R13-S13 -> 0 | W13: =U13-V13 -> 0 | Z13: =X13-Y13 -> 0 | AC13: =AA13-AB13 -> 0 | AF13: =AD13-AE13 -> 0
A14: ITA (USD tr) | K14: =I14-J14 -> 0 | N14: =L14-M14 -> 0 | Q14: =O14-P14 -> 0 | T14: =R14-S14 -> 0 | W14: =U14-V14 -> 0 | Z14: =X14-Y14 -> 0 | AC14: =AA14-AB14 -> 0 | AF14: =AD14-AE14 -> 0
A15: Frente Corretora | K15: =I15-J15 -> 0 | N15: =L15-M15 -> 0 | Q15: =O15-P15 -> 0
A16: TOTAL: | B16: =SUM(B4:B14) -> 99997.663 | C16: =SUM(C4:C14) -> 0 | D16: =SUM(D4:D14) -> 0 | E16: =SUM(E4:E14) -> 0 | F16: =SUM(F4:F14) -> 0 | G16: =SUM(G4:G14) -> 0 | H16: =SUM(H4:H14) -> 0 | I16: =SUM(I4:I14) -> 160616.68 | ... N16: =SUM(N4:N14) -> 120880.74 | O16: =SUM(O4:O15) -> 173035.71 | P16: =SUM(P4:P15) -> 137564.07 | Q16: =SUM(Q4:Q14) -> 35471.64 | R16: =SUM(R4:R15) -> 159964.71 | S16: =SUM(S4:S15) -> 115746.72 | T16: =SUM(T4:T14) -> 44217.99 | U16: =SUM(U4:U14) -> 145836.4 | V16: =SUM(V4:V14) -> 112388.77 | W16: =SUM(W4:W14) -> 33447.63 | X16: =SUM(X4:X14) -> 97359.529 | Y16: =SUM(Y4:Y14) -> -129723.84 | Z16: =SUM(Z4:Z14) -> -32364.31 | AA16: =SUM(AA4:AA14) -> 170389.61 | ... AF16: =SUM(AF4:AF14) -> 5848.5013
A17: Incentivos Contrapartida | B17: 0 | C17: 0
A18: Incentivos Livres | B18: 0 | C18: 0
A19: TOTAL C/ Incentivos | B19: =SUM(B16:B18) -> 99997.663 | C19: =SUM(C16:C18) -> 0 | D19: =SUM(D16:D18) -> 0 | E19: =SUM(E16:E18) -> 0 | F19: =SUM(F16:F18) -> 0 | G19: =SUM(G16:G18) -> 0 | H19: =SUM(H16:H18) -> 0 | I19: =SUM(I16:I18) -> 160616.68 | L19: =SUM(L16:L18) -> 260829.19 | Q19: =SUM(Q16:Q18) -> 35471.64 | R19: =SUM(R16:R18) -> 159964.71 | U19: =SUM(U16:U18) -> 145836.4 | X19: =SUM(X16:X18) -> 97359.529 | AA19: =SUM(AA16:AA18) -> 170389.61 | AD19: =SUM(AD16:AD18) -> 111700.88
A20: PL
A21: ROA | B21: =B19/B20 -> #DIV/0! | C21: =C19/C20 -> #DIV/0! | D21: =D19/D20 -> #DIV/0! | E21: =E19/E20 -> #DIV/0! | F21: =F19/F20 -> #DIV/0! | G21: =G19/G20 -> #DIV/0! | H21: =H19/H20 -> #DIV/0! | I21: =I19/I20 -> #DIV/0! | L21: =L19/L20 -> #DIV/0! | Q21: =Q19/Q20 -> #DIV/0! | R21: =R19/R20 -> #DIV/0! | U21: =U19/U20 -> #DIV/0! | X21: =X19/X20 -> #DIV/0! | AA21: =AA19/AA20 -> #DIV/0! | AD21: =AD19/AD20 -> #DIV/0!
A23: RESULTADO SEM O QUANTUM | L23: =L16-L10 -> 121148.61 | M23: =M16-M10 -> 86116.99 | N23: =N16-N10 -> 35031.62 | O23: =O16-O10 -> 143289.71 | P23: =P16-P10 -> 124782.79 | Q23: =Q16-Q10 -> 18506.92 | R23: =R16-R10 -> 147376.71 | S23: =S16-S10 -> 111061.09 | ... AF23: =AF16-AF10 -> 5848.5013
B26: Faturado
B27: Pago
B28: Pendente
